{
  "$type" : "TCardSkill",
  "StartingTier" : "Bronze",
  "Tiers" : {
    "Bronze" : {
      "AbilityIds" : [ ],
      "ActiveTooltipIds" : [ ],
      "Attributes" : {
        "Multicast" : 1
      },
      "AuraIds" : [ "0" ],
      "PassiveTooltipIds" : [ 0 ]
    },
    "Silver" : {
      "AbilityIds" : [ ],
      "ActiveTooltipIds" : [ ],
      "Attributes" : { },
      "AuraIds" : [ "0" ],
      "PassiveTooltipIds" : [ 0 ]
    },
    "Gold" : {
      "AbilityIds" : [ ],
      "ActiveTooltipIds" : [ ],
      "Attributes" : { },
      "AuraIds" : [ "0" ],
      "PassiveTooltipIds" : [ 0 ]
    },
    "Diamond" : {
      "AbilityIds" : [ ],
      "ActiveTooltipIds" : [ ],
      "Attributes" : { },
      "AuraIds" : [ "0" ],
      "PassiveTooltipIds" : [ 0 ]
    }
  },
  "Type" : "Skill",
  "Id" : "1eebbbc3-595a-485c-be96-0755c9c7c2a5",
  "Version" : "1.0.0",
  "InternalName" : "Toxic Spores",
  "InternalDescription" : "",
  "Size" : "Medium",
  "Heroes" : [ "Vanessa", "Dooley", "Mak" ],
  "Tags" : [ ],
  "HiddenTags" : [ "PoisonReference" ],
  "ArtKey" : "Icon_Skill_ToxicSpores.png",
  "SpawningEligibility" : "Always",
  "CardPackId" : "Vanessa_Core",
  "TranslationKey" : "33085f03cc46788f7cf0b196767f350a",
  "AudioKey" : "",
  "Localization" : {
    "Description" : null,
    "FlavorText" : null,
    "Title" : {
      "Key" : "33085f03cc46788f7cf0b196767f350a",
      "Text" : "Toxic Spores"
    },
    "Tooltips" : [ {
      "Key" : "33085f03cc46788f7cf0b196767f350a",
      "Text" : "Your Small items have +{aura.0} Poison."
    } ]
  },
  "Abilities" : { },
  "Auras" : {
    "0" : {
      "Id" : "0",
      "InternalName" : "Toxic Spores",
      "InternalDescription" : "Your Small items have +{aura.0} Poison.",
      "Action" : {
        "$type" : "TAuraActionCardModifyAttribute",
        "AttributeType" : "PoisonApplyAmount",
        "Operation" : "Add",
        "Value" : {
          "$type" : "TFixedValue",
          "Value" : 1.0
        },
        "Target" : {
          "$type" : "TTargetCardSection",
          "TargetSection" : "SelfHand",
          "ExcludeSelf" : false,
          "Conditions" : {
            "$type" : "TCardConditionalSize",
            "Sizes" : [ "Small" ],
            "IsNot" : false
          }
        }
      },
      "MigrationData" : "7462788c-f826-400a-aebc-477b209bf2c6",
      "Prerequisites" : null,
      "TranslationKey" : "33085f03cc46788f7cf0b196767f350a",
      "VFXConfig" : {
        "VFXIsTakeover" : false,
        "VFXOverrideKey" : null,
        "VFXShouldPlay" : true
      }
    }
  }
}