{
  "$type" : "TCardSkill",
  "StartingTier" : "Diamond",
  "Tiers" : {
    "Diamond" : {
      "Attributes" : {
        "BuyPrice" : 40,
        "ChargeAmount" : 1000,
        "ChargeTargets" : 1
      },
      "AbilityIds" : [ "0" ],
      "AuraIds" : [ ],
      "TooltipIds" : [ 0 ]
    }
  },
  "Type" : "Skill",
  "Id" : "6e95c90d-e4b4-42c3-b5e9-3c390d762c92",
  "Version" : "1.0.0",
  "InternalName" : "Shield Bash",
  "InternalDescription" : "",
  "Size" : "Medium",
  "Heroes" : [ "Vanessa", "Pygmalien", "Dooley", "Stelle" ],
  "Tags" : [ ],
  "HiddenTags" : [ ],
  "ArtKey" : "Icon_Skill_Conditioning.png",
  "CardPackId" : "Vanessa_Core",
  "TranslationKey" : "d225c8ba02b1d8aa915ca35fdc3bc68e",
  "AudioKey" : "",
  "Localization" : {
    "Title" : {
      "Key" : "d225c8ba02b1d8aa915ca35fdc3bc68e",
      "Text" : "Shield Bash"
    },
    "Description" : null,
    "FlavorText" : null,
    "Tooltips" : [ {
      "Content" : {
        "Key" : "d225c8ba02b1d8aa915ca35fdc3bc68e",
        "Text" : "When your enemy uses a non-weapon item, charge a weapon {ability.0} second."
      },
      "TooltipType" : "Passive"
    } ]
  },
  "Abilities" : {
    "0" : {
      "Id" : "0",
      "Trigger" : {
        "$type" : "TTriggerOnItemUsed",
        "Subject" : {
          "$type" : "TTargetCardSection",
          "TargetSection" : "OpponentHand",
          "ExcludeSelf" : false,
          "Conditions" : {
            "$type" : "TCardConditionalTag",
            "Tags" : [ "Weapon" ],
            "Operator" : "None"
          }
        }
      },
      "ActiveIn" : "HandOnly",
      "Action" : {
        "$type" : "TActionCardCharge",
        "Target" : {
          "$type" : "TTargetCardRandom",
          "ExcludeSelf" : false,
          "TargetSection" : "SelfHand",
          "Conditions" : {
            "$type" : "TCardConditionalTag",
            "Tags" : [ "Weapon" ],
            "Operator" : "Any"
          }
        }
      },
      "Prerequisites" : null,
      "Priority" : "Low",
      "InternalName" : "Shield Bash",
      "InternalDescription" : "",
      "MigrationData" : "9b98dd6d-83c7-4ea4-9630-7b97fdf52638",
      "VFXConfig" : {
        "VFXOverrideKey" : null,
        "VFXShouldPlay" : true,
        "VFXIsTakeover" : false
      },
      "TranslationKey" : "d225c8ba02b1d8aa915ca35fdc3bc68e"
    }
  },
  "Auras" : { }
}