{
  "$type" : "TCardSkill",
  "StartingTier" : "Gold",
  "Tiers" : {
    "Gold" : {
      "Attributes" : {
        "FreezeAmount" : 1000,
        "FreezeTargets" : 1,
        "BuyPrice" : 20,
        "Custom_0" : 0
      },
      "AbilityIds" : [ "0", "1" ],
      "AuraIds" : [ ],
      "TooltipIds" : [ 0 ]
    },
    "Diamond" : {
      "Attributes" : {
        "FreezeAmount" : 2000,
        "BuyPrice" : 40
      },
      "AbilityIds" : [ "0", "1" ],
      "AuraIds" : [ ],
      "TooltipIds" : [ 0 ]
    }
  },
  "Type" : "Skill",
  "Id" : "dec273b3-155e-4fbd-9629-5dbd2900e032",
  "Version" : "1.0.0",
  "InternalName" : "Coolant Leak",
  "InternalDescription" : "",
  "Size" : "Medium",
  "Heroes" : [ "Pygmalien", "Dooley", "Jules", "Mak" ],
  "Tags" : [ ],
  "HiddenTags" : [ "Freeze" ],
  "ArtKey" : "Icon_Skill_CoolantLeak.png",
  "CardPackId" : "Vanessa_Core",
  "TranslationKey" : "0396e927fe36bfdb7552c4e0316126c4",
  "AudioKey" : "",
  "Localization" : {
    "Title" : {
      "Key" : "0396e927fe36bfdb7552c4e0316126c4",
      "Text" : "Coolant Leak"
    },
    "Description" : null,
    "FlavorText" : null,
    "Tooltips" : [ {
      "Content" : {
        "Key" : "692425a1289c1826ae25460dc4b6a018",
        "Text" : "The first 5 times you use your rightmost item, freeze {ability.0.targets} item for {ability.0} second(s)."
      },
      "TooltipType" : "Passive"
    } ]
  },
  "Abilities" : {
    "0" : {
      "Id" : "0",
      "Trigger" : {
        "$type" : "TTriggerOnItemUsed",
        "Subject" : {
          "$type" : "TTargetCardXMost",
          "TargetSection" : "SelfHand",
          "TargetMode" : "RightMostCard",
          "ExcludeSelf" : true,
          "Conditions" : null
        }
      },
      "ActiveIn" : "HandOnly",
      "Action" : {
        "$type" : "TActionCardFreeze",
        "Target" : {
          "$type" : "TTargetCardRandom",
          "ExcludeSelf" : false,
          "TargetSection" : "OpponentHand",
          "Conditions" : null
        }
      },
      "Prerequisites" : [ {
        "$type" : "TPrerequisiteCardCount",
        "Subject" : {
          "$type" : "TTargetCardSelf",
          "Conditions" : {
            "$type" : "TCardConditionalAttribute",
            "Attribute" : "Custom_0",
            "ComparisonOperator" : "LessThanOrEqual",
            "ComparisonValue" : {
              "$type" : "TFixedValue",
              "Value" : 4.0
            }
          }
        },
        "Comparison" : "Equal",
        "Amount" : 1
      } ],
      "Priority" : "Medium",
      "InternalName" : "Coolant Leak Skill OnRightmostUse Freeze/1",
      "InternalDescription" : "When you use your rightmost item, freeze an item for {ability.0} second(s).",
      "MigrationData" : "24f9c75a-7696-4ff6-b620-e2885aa4ecf5",
      "VFXConfig" : {
        "VFXOverrideKey" : null,
        "VFXShouldPlay" : true,
        "VFXIsTakeover" : false
      },
      "TranslationKey" : "692425a1289c1826ae25460dc4b6a018"
    },
    "1" : {
      "Id" : "1",
      "Trigger" : {
        "$type" : "TTriggerOnItemUsed",
        "Subject" : {
          "$type" : "TTargetCardXMost",
          "TargetSection" : "SelfHand",
          "TargetMode" : "RightMostCard",
          "ExcludeSelf" : true,
          "Conditions" : null
        }
      },
      "ActiveIn" : "HandOnly",
      "Action" : {
        "$type" : "TActionCardModifyAttribute",
        "Value" : {
          "$type" : "TFixedValue",
          "Value" : 1.0
        },
        "AttributeType" : "Custom_0",
        "Operation" : "Add",
        "Duration" : {
          "$type" : "TDeterminantDuration",
          "DurationType" : "UntilEndOfCombat"
        },
        "TargetCount" : null,
        "Target" : {
          "$type" : "TTargetCardSelf",
          "Conditions" : null
        }
      },
      "Prerequisites" : null,
      "Priority" : "Medium",
      "InternalName" : "Counter Increment",
      "InternalDescription" : "",
      "MigrationData" : "ca935468-9cab-4627-874b-66d353ed7b09",
      "VFXConfig" : {
        "VFXOverrideKey" : null,
        "VFXShouldPlay" : true,
        "VFXIsTakeover" : false
      },
      "TranslationKey" : "addd58cb20c13b02b433940601a41d13"
    }
  },
  "Auras" : { }
}