{
  "EffectPriority" : "Medium",
  "AttributeReference" : null,
  "ShowRefValue" : true,
  "ScaleWithTier" : true,
  "InternalName" : "",
  "EffectModifyMode" : "Add",
  "EffectType" : "CardAttributeModifier",
  "EffectDataType" : 3,
  "EffectDataId" : 4,
  "ConditionalPrerequisiteDataId" : "45cf93a6-83c6-4272-8166-21a36d64594b",
  "TriggerPrerequisiteDataId1" : "00000000-0000-0000-0000-000000000000",
  "TriggerPrerequisiteDataId2" : "00000000-0000-0000-0000-000000000000",
  "IsEffectTriggered" : false,
  "TargetType" : "PlayerBoard",
  "TargetPrerequisiteDataId1" : "0b40d80f-e54b-41b3-a6b6-769c0d4fec70",
  "TargetPrerequisiteDataId2" : "00000000-0000-0000-0000-000000000000",
  "Trigger" : "OnPlaced",
  "TriggerCount" : 0,
  "DataInt" : [ 5, 0, 0, 0, 0, 0, 0, 0, 0, 0 ],
  "DataFloat" : [ 1.0, 0.0, 0.0, 0.0, 0.0, 0.0, 0.0, 0.0, 0.0, 0.0 ],
  "VFXOverrideKey" : "Invalid",
  "Id" : "42c3fdf0-1e8e-4581-885e-c13346e40714",
  "Name" : "Effect - Buddy System 2",
  "Keyword" : "",
  "BazaarType" : "Invalid",
  "DeleteDate" : ""
}