{
  "EffectPriority" : "Low",
  "AttributeReference" : null,
  "ShowRefValue" : true,
  "ScaleWithTier" : true,
  "InternalName" : "",
  "EffectModifyMode" : "Add",
  "EffectType" : "CardAttributeModifier",
  "EffectDataType" : 9,
  "EffectDataId" : 1,
  "ConditionalPrerequisiteDataId" : "00000000-0000-0000-0000-000000000000",
  "TriggerPrerequisiteDataId1" : "1e1355e3-fa5b-435d-a8fa-ba2e92a43487",
  "TriggerPrerequisiteDataId2" : "e935343f-058a-4eee-a01e-ea618a09277e",
  "IsEffectTriggered" : false,
  "TargetType" : "Self",
  "TargetPrerequisiteDataId1" : "00000000-0000-0000-0000-000000000000",
  "TargetPrerequisiteDataId2" : "00000000-0000-0000-0000-000000000000",
  "Trigger" : "OnItemUse",
  "TriggerCount" : 0,
  "DataInt" : [ 1000, 0, 0, 0, 0, 0, 0, 0, 0, 0 ],
  "DataFloat" : [ 0.0, 0.0, 1.0, 0.0, 0.0, 0.0, 0.0, 0.0, 0.0, 0.0 ],
  "VFXOverrideKey" : "Invalid",
  "Id" : "446bf9bf-ee3d-4474-a747-d17a6c19ddbf",
  "Name" : "Effect - Anchor 3",
  "Keyword" : "When you use another Medium item, give this Haste for {i} seconds.",
  "BazaarType" : "Invalid",
  "DeleteDate" : ""
}