{
  "EffectPriority" : "Low",
  "AttributeReference" : null,
  "ShowRefValue" : true,
  "ScaleWithTier" : true,
  "InternalName" : "",
  "EffectModifyMode" : "Add",
  "EffectType" : "CardAttributeModifier",
  "EffectDataType" : 12,
  "EffectDataId" : 1,
  "ConditionalPrerequisiteDataId" : "00000000-0000-0000-0000-000000000000",
  "TriggerPrerequisiteDataId1" : "21b339c1-edfc-4a3e-8aa7-6101d9eed32c",
  "TriggerPrerequisiteDataId2" : "00000000-0000-0000-0000-000000000000",
  "IsEffectTriggered" : false,
  "TargetType" : "TriggerSource",
  "TargetPrerequisiteDataId1" : "00000000-0000-0000-0000-000000000000",
  "TargetPrerequisiteDataId2" : "00000000-0000-0000-0000-000000000000",
  "Trigger" : "OnItemUse",
  "TriggerCount" : 0,
  "DataInt" : [ 1000, 0, 0, 0, 0, 0, 0, 0, 0, 0 ],
  "DataFloat" : [ 0.0, 0.0, 0.0, 0.0, 0.0, 0.0, 0.0, 0.0, 0.0, 0.0 ],
  "VFXOverrideKey" : "Invalid",
  "Id" : "53f02150-a4b5-4331-ae3a-0339cf38ce05",
  "Name" : "Effect - Iceberg",
  "Keyword" : "When your enemy uses an item, Freeze it for {i} seconds.",
  "BazaarType" : "Invalid",
  "DeleteDate" : null
}