{
  "EffectPriority" : "Medium",
  "AttributeReference" : null,
  "ShowRefValue" : true,
  "ScaleWithTier" : true,
  "InternalName" : "",
  "EffectModifyMode" : "Add",
  "EffectType" : "PlayerAttributeModifier",
  "EffectDataType" : 4,
  "EffectDataId" : 1,
  "ConditionalPrerequisiteDataId" : "00000000-0000-0000-0000-000000000000",
  "TriggerPrerequisiteDataId1" : "00000000-0000-0000-0000-000000000000",
  "TriggerPrerequisiteDataId2" : "00000000-0000-0000-0000-000000000000",
  "IsEffectTriggered" : false,
  "TargetType" : "Player",
  "TargetPrerequisiteDataId1" : "00000000-0000-0000-0000-000000000000",
  "TargetPrerequisiteDataId2" : "00000000-0000-0000-0000-000000000000",
  "Trigger" : "OnCombat",
  "TriggerCount" : 0,
  "DataInt" : [ 20, 0, 0, 0, 0, 0, 0, 0, 0, 0 ],
  "DataFloat" : [ 0.0, 0.0, 1.0, 0.0, 0.0, 0.0, 0.0, 0.0, 0.0, 0.0 ],
  "VFXOverrideKey" : "Invalid",
  "Id" : "5ef73deb-4172-4e4c-aaad-55f6503ea4eb",
  "Name" : "Effect - Marble Scalemail - 1",
  "Keyword" : "Shield {i}",
  "BazaarType" : "Invalid",
  "DeleteDate" : null
}